langchain_localai/__init__.py
langchain_localai/localai_embeddings.py
langchain_localai/py.typed
langchain_localai-0.1.2.dist-info/LICENSE
langchain_localai-0.1.2.dist-info/METADATA
langchain_localai-0.1.2.dist-info/WHEEL
langchain_localai-0.1.2.dist-info/RECORD
