Metadata-Version: 2.1
Name: langchain-localai
Version: 0.1.2
Summary: An integration package connecting LocalAI and LangChain
Home-page: https://github.com/mkhludnev/langchain-localai
License: MIT
Requires-Python: >=3.9,<4.0
Classifier: License :: OSI Approved :: MIT License
Classifier: Programming Language :: Python :: 3
Classifier: Programming Language :: Python :: 3.9
Classifier: Programming Language :: Python :: 3.10
Classifier: Programming Language :: Python :: 3.11
Classifier: Programming Language :: Python :: 3.12
Requires-Dist: langchain-core (>=0.3.15,<0.4.0)
Requires-Dist: openai (>=1.30.0,<2.0)
Project-URL: Repository, https://github.com/mkhludnev/langchain-localai
Project-URL: Release Notes, https://github.com/mkhludnev/langchain-localai/releases?&expanded=true
Project-URL: Source Code, https://github.com/mkhludnev/langchain-localai/tree/main/libs/localai
